.git_archival.txt
.gitattributes
.gitignore
CHANGELOG.md
LICENSE
MANIFEST.in
README.md
requirements.txt
setup.cfg
setup.py
.circleci/config.yml
bin/mdshare-index-maker.py
mdshare/__init__.py
mdshare/api.py
mdshare/repository.py
mdshare/utils.py
mdshare.egg-info/PKG-INFO
mdshare.egg-info/SOURCES.txt
mdshare.egg-info/dependency_links.txt
mdshare.egg-info/not-zip-safe
mdshare.egg-info/requires.txt
mdshare.egg-info/top_level.txt
mdshare/data/mdshare-catalogue.md5
mdshare/data/mdshare-catalogue.yaml
mdshare/data/template.yaml
mdshare/test/__init__.py
mdshare/test/test_api.py
mdshare/test/test_repository.py
mdshare/test/test_utils.py